{
  "credit": "Made with Blockbench",
  "parent": "builtin/entity",
  "texture_size": [
    64,
    64
  ],
  "display": {
    "thirdperson_righthand": {
      "rotation": [
        60,
        0,
        0
      ],
      "translation": [
        0,
        -5,
        -15
      ],
      "scale": [
        0.75,
        0.75,
        0.75
      ]
    },
    "thirdperson_lefthand": {
      "rotation": [
        60,
        0,
        0
      ],
      "translation": [
        0,
        -5,
        -15
      ],
      "scale": [
        0.75,
        0.75,
        0.75
      ]
    },
    "firstperson_righthand": {
      "translation": [
        -2,
        -15,
        0
      ],
      "scale": [
        0.75,
        0.75,
        0.75
      ]
    },
    "firstperson_lefthand": {
      "translation": [
        -2,
        -15,
        0
      ],
      "scale": [
        0.75,
        0.75,
        0.75
      ]
    },
    "ground": {
      "translation": [
        0,
        -14,
        -3
      ]
    },
    "gui": {
      "rotation": [
        30,
        30,
        0
      ],
      "translation": [
        -1,
        -10.5,
        0
      ],
      "scale": [
        0.75,
        0.75,
        0.75
      ]
    },
    "head": {
      "rotation": [
        -95,
        0,
        0
      ],
      "translation": [
        0,
        5,
        19
      ]
    },
    "fixed": {
      "rotation": [
        0,
        -180,
        0
      ],
      "translation": [
        0,
        -18,
        0
      ]
    }
  },
  "textures": {
    "particle": "item/tan_backpack"
  }
}